aurigma/design_atoms/__init__.py
aurigma/design_atoms/api_client.py
aurigma/design_atoms/api_response.py
aurigma/design_atoms/configuration.py
aurigma/design_atoms/exceptions.py
aurigma/design_atoms/py.typed
aurigma/design_atoms/rest.py
aurigma/design_atoms/api/__init__.py
aurigma/design_atoms/api/build_info_api.py
aurigma/design_atoms/api/design_atoms_compatibility_api.py
aurigma/design_atoms/api/design_atoms_images_api.py
aurigma/design_atoms/api/design_atoms_mockups2d_api.py
aurigma/design_atoms/api/design_atoms_mockups3d_api.py
aurigma/design_atoms/api/design_atoms_palettes_api.py
aurigma/design_atoms/api/design_atoms_print_product_api.py
aurigma/design_atoms/api/design_atoms_print_product_items_api.py
aurigma/design_atoms/api/design_atoms_service_api.py
aurigma/design_atoms/api/design_atoms_viewer_api.py
aurigma/design_atoms/models/__init__.py
aurigma/design_atoms/models/apply_design_items_data_model.py
aurigma/design_atoms/models/batch_create_items_from_storage_model.py
aurigma/design_atoms/models/batch_create_items_from_url_model.py
aurigma/design_atoms/models/build_info_model.py
aurigma/design_atoms/models/conflict_type.py
aurigma/design_atoms/models/convert_colors_model.py
aurigma/design_atoms/models/create_design_model.py
aurigma/design_atoms/models/create_item_from_storage_model.py
aurigma/design_atoms/models/create_item_from_url_model.py
aurigma/design_atoms/models/design_element_processing_conflict_dto.py
aurigma/design_atoms/models/design_element_type.py
aurigma/design_atoms/models/design_info.py
aurigma/design_atoms/models/design_item_data_model.py
aurigma/design_atoms/models/design_item_font_settings_model.py
aurigma/design_atoms/models/design_parameters.py
aurigma/design_atoms/models/design_print_area_dto.py
aurigma/design_atoms/models/design_print_area_params.py
aurigma/design_atoms/models/design_surface_container_dto.py
aurigma/design_atoms/models/design_surface_dto.py
aurigma/design_atoms/models/design_surface_item_dto.py
aurigma_design_atoms_api_client-1.0.0.dist-info/METADATA
aurigma_design_atoms_api_client-1.0.0.dist-info/WHEEL
aurigma_design_atoms_api_client-1.0.0.dist-info/top_level.txt
aurigma_design_atoms_api_client-1.0.0.dist-info/RECORD
